jtnnencoder/__init__.py
jtnnencoder/jtnnencoder.py
jtnnencoder/data/__init__.py
jtnnencoder/data/vocab.txt
jtnnencoder/jtnn/__init__.py
jtnnencoder/jtnn/chemutils.py
jtnnencoder/jtnn/datautils.py
jtnnencoder/jtnn/jtmpn.py
jtnnencoder/jtnn/jtnn_dec.py
jtnnencoder/jtnn/jtnn_enc.py
jtnnencoder/jtnn/jtnn_vae.py
jtnnencoder/jtnn/jtprop_vae.py
jtnnencoder/jtnn/mol_tree.py
jtnnencoder/jtnn/mpn.py
jtnnencoder/jtnn/nnutils.py
jtnnencoder/models/__init__.py
jtnnencoder/models/model.iter-4
jtnnencoder-0.1.dist-info/LICENSE
jtnnencoder-0.1.dist-info/METADATA
jtnnencoder-0.1.dist-info/WHEEL
jtnnencoder-0.1.dist-info/top_level.txt
jtnnencoder-0.1.dist-info/RECORD
