Metadata-Version: 2.1
Name: jtnnencoder
Version: 0.1
Summary: An Easy to install version of the jtnn encoder for generation of latent molecule features.
Home-page: https://github.com/LiamWilbraham/jtnnencoder
Author: Liam Wilbraham
Author-email: liam.wilbrahaml@glasgow.ac.uk
License: MIT
Download-URL: https://github.com/LiamWilbraham/jtnnencoder/archive/v_01.tar.gz
Keywords: cheminformatics,chemistry
Platform: UNKNOWN
Classifier: License :: OSI Approved :: MIT License
Classifier: Programming Language :: Python :: 3
Requires-Dist: numpy
Requires-Dist: scipy
